MANIFEST.in
README.rst
setup.cfg
setup.py
djmicrosip_redis/EventLog.dll
djmicrosip_redis/Redis on Windows Release Notes.docx
djmicrosip_redis/Redis on Windows.docx
djmicrosip_redis/Windows Service Documentation.docx
djmicrosip_redis/__init__.py
djmicrosip_redis/__init__.pyc
djmicrosip_redis/dump.rdb
djmicrosip_redis/redis-benchmark.exe
djmicrosip_redis/redis-check-aof.exe
djmicrosip_redis/redis-check-dump.exe
djmicrosip_redis/redis-cli.exe
djmicrosip_redis/redis-server.exe
djmicrosip_redis/redis-server.pdb
djmicrosip_redis/redis.windows-service.conf
djmicrosip_redis/redis.windows.conf
djmicrosip_redis.egg-info/PKG-INFO
djmicrosip_redis.egg-info/SOURCES.txt
djmicrosip_redis.egg-info/dependency_links.txt
djmicrosip_redis.egg-info/top_level.txt